[
  {
    "username": "nashplant0",
    "email": "mashplant0@vk.com",
    "displayName": "Ashplant",
    "dateOfBirth": "29/01/1993"
  },
  {
    "username": "vnucci1",
    "email": "lnucci1@paypal.com",
    "displayName": "Nucci",
    "dateOfBirth": "22/12/1985"
  },
  {
    "username": "clawling2",
    "email": "flawling2@ucla.edu",
    "displayName": "Lawling",
    "dateOfBirth": "14/06/1996"
  },
  {
    "username": "dgajewski3",
    "email": "bgajewski3@thetimes.co.uk",
    "displayName": "Gajewski",
    "dateOfBirth": "01/12/1992"
  },
  {
    "username": "cgrannell4",
    "email": "tgrannell4@biglobe.ne.jp",
    "displayName": "Grannell",
    "dateOfBirth": "18/11/2000"
  },
  {
    "username": "aluparti5",
    "email": "eluparti5@mozilla.org",
    "displayName": "Luparti",
    "dateOfBirth": "10/03/1984"
  },
  {
    "username": "rrickersey6",
    "email": "crickersey6@tumblr.com",
    "displayName": "Rickersey",
    "dateOfBirth": "13/07/1999"
  },
  {
    "username": "mhabert7",
    "email": "nhabert7@oaic.gov.au",
    "displayName": "Habert",
    "dateOfBirth": "30/12/1980"
  },
  {
    "username": "jmatczak8",
    "email": "hmatczak8@cnbc.com",
    "displayName": "Matczak",
    "dateOfBirth": "20/01/1993"
  },
  {
    "username": "eplumridege9",
    "email": "gplumridege9@nifty.com",
    "displayName": "Plumridege",
    "dateOfBirth": "27/12/1983"
  }
]
